setup.cfg
setup.py
bin/pymkd
pymkd/__init__.py
pymkd/entitytrans.py
pymkd/pymkd.py
pymkd.egg-info/PKG-INFO
pymkd.egg-info/SOURCES.txt
pymkd.egg-info/dependency_links.txt
pymkd.egg-info/requires.txt
pymkd.egg-info/top_level.txt
test/test_pymkd.py