Metadata-Version: 1.1
Name: pymkd
Version: 0.2.33
Summary: Markdown Parser in python, compatible with CommonMark
Home-page: https://github.com/lotabout/pymkd
Author: Jinzhou Zhang
Author-email: lotabout@gmail.com
License: MIT
Download-URL: https://github.com/lotabout/pymkd/archive/v0.2.33.tar.gz
Keywords: markup,markdown,commonmark
Platform: UNKNOWN
